pywechat/Clock.py
pywechat/Errors.py
pywechat/Uielements.py
pywechat/Warnings.py
pywechat/WechatAuto.py
pywechat/WechatTools.py
pywechat/WinSettings.py
pywechat/__init__.py
pywechat/utils.py
pywechat/ffmpeg/__init__.py
pywechat/ffmpeg/ffmpeg.exe
pyweixin/Clock.py
pyweixin/Errors.py
pyweixin/Uielements.py
pyweixin/Warnings.py
pyweixin/WechatAuto.py
pyweixin/WechatTools.py
pyweixin/WinSettings.py
pyweixin/__init__.py
pywechat127-1.9.7.dist-info/METADATA
pywechat127-1.9.7.dist-info/WHEEL
pywechat127-1.9.7.dist-info/top_level.txt
pywechat127-1.9.7.dist-info/RECORD
