Metadata-Version: 2.1
Name: pywechat127
Version: 1.9.7
Summary: A Powerful Windows-PC-Wechat automation Tool
Home-page: https://github.com/Hello-Mr-Crab/pywechat
Author: Hello-Mr-Crab
Author-email: 3083256475@qq.com
License: LGPL
Keywords: rpa,windows,wechat,automation
Platform: Windows
Classifier: Operating System :: Microsoft :: Windows
Requires-Dist: emoji >=2.14.1
Requires-Dist: PyAutoGUI >=0.9.54
Requires-Dist: pycaw >=20240210
Requires-Dist: pywin32 >=308
Requires-Dist: pywin32-ctypes >=0.2.2
Requires-Dist: pywinauto >=0.6.8
Requires-Dist: psutil >=5.9.6
Requires-Dist: pillow >=11.1.0
